bub/__init__.py
bub/config.py
bub/agent/__init__.py
bub/agent/context.py
bub/agent/core.py
bub/agent/runtime.py
bub/agent/tools.py
bub/cli/__init__.py
bub/cli/app.py
bub/cli/render.py
bub/tools/__init__.py
bub/tools/file_edit.py
bub/tools/file_read.py
bub/tools/file_write.py
bub/tools/run_command.py
bub/tools/utils.py
bub-0.1.1.dist-info/METADATA
bub-0.1.1.dist-info/WHEEL
bub-0.1.1.dist-info/entry_points.txt
bub-0.1.1.dist-info/licenses/LICENSE
bub-0.1.1.dist-info/RECORD
