Metadata-Version: 2.4
Name: bub
Version: 0.1.1
Summary: Bub it. Build it.
Project-URL: Homepage, https://bub.build
Project-URL: Repository, https://github.com/psiace/bub
Project-URL: Documentation, https://bub.build
Author-email: Chojan Shang <psiace@apache.org>
License-File: LICENSE
Keywords: python
Classifier: Intended Audience :: Developers
Classifier: Programming Language :: Python
Classifier: Programming Language :: Python :: 3
Classifier: Programming Language :: Python :: 3.12
Classifier: Programming Language :: Python :: 3.13
Classifier: Topic :: Software Development :: Libraries :: Python Modules
Requires-Python: <4.0,>=3.12
Requires-Dist: any-llm-sdk[anthropic,aws,azure,google,openai]>=0.1.1
Requires-Dist: eventure>=0.4.0
Requires-Dist: huey>=2.5.0
Requires-Dist: pydantic-settings>=2.0.0
Requires-Dist: pydantic>=2.0.0
Requires-Dist: rich>=13.0.0
Requires-Dist: typer>=0.9.0
Requires-Dist: uuid-extension>=0.2.0
